timer/AboutDialog.py
timer/App.py
timer/TimerDialog.py
timer/TimerWidget.py
timer/__init__.py
timer/lib/ConfMixin.py
timer/lib/Dialog.py
timer/lib/InfoText.py
timer/lib/InvokeMixin.py
timer/lib/MyListbox.py
timer/lib/Settings.py
timer/lib/TreeDB.py
timer/lib/__init__.py
timer/lib/misc.py
timer/resource/__init__.py
timer/resource/image/Timer.png
T_i_m_e_r-0.1.0.dist-info/LICENSE.txt
T_i_m_e_r-0.1.0.dist-info/METADATA
T_i_m_e_r-0.1.0.dist-info/WHEEL
T_i_m_e_r-0.1.0.dist-info/entry_points.txt
T_i_m_e_r-0.1.0.dist-info/top_level.txt
T_i_m_e_r-0.1.0.dist-info/RECORD
