Metadata-Version: 2.1
Name: T-i-m-e-r
Version: 0.1.0
Summary: A better count-down timer in tkinter
Home-page: https://github.com/feng-lei/timer-tkinter
Author: Fenglei Zhang
Author-email: fenglei4518@hotmail.com
License: UNKNOWN
Keywords: countdown,timer,tkinter
Platform: any
Classifier: Development Status :: 3 - Alpha
Classifier: Intended Audience :: End Users/Desktop
Classifier: Programming Language :: Python :: 3
Classifier: License :: OSI Approved :: MIT License
Classifier: Operating System :: OS Independent
Classifier: Topic :: Utilities
Classifier: Topic :: Office/Business
Requires-Python: >=3.6
